uois_toolkit/__init__.py
uois_toolkit/config/__init__.py
uois_toolkit/config/config.py
uois_toolkit/datasets/__init__.py
uois_toolkit/datasets/base.py
uois_toolkit/datasets/iteach_humanplay.py
uois_toolkit/datasets/ocid.py
uois_toolkit/datasets/osd.py
uois_toolkit/datasets/robot_pushing.py
uois_toolkit/datasets/tabletop.py
uois_toolkit/datasets/utils/__init__.py
uois_toolkit/datasets/utils/augmentation.py
uois_toolkit/datasets/utils/blob.py
uois_toolkit/datasets/utils/mask.py
uois_toolkit/datasets/utils/seed.py
uois_toolkit/metrics/__init__.py
uois_toolkit/metrics/evaluation_metrics.py
uois_toolkit-0.1.2.dist-info/licenses/LICENSE
venv_pypi/Lib/site-packages/build/__init__.py
venv_pypi/Lib/site-packages/build/__main__.py
venv_pypi/Lib/site-packages/build/_builder.py
venv_pypi/Lib/site-packages/build/_ctx.py
venv_pypi/Lib/site-packages/build/_exceptions.py
venv_pypi/Lib/site-packages/build/_types.py
venv_pypi/Lib/site-packages/build/_util.py
venv_pypi/Lib/site-packages/build/env.py
venv_pypi/Lib/site-packages/build/py.typed
venv_pypi/Lib/site-packages/build/util.py
venv_pypi/Lib/site-packages/build/_compat/__init__.py
venv_pypi/Lib/site-packages/build/_compat/importlib.py
venv_pypi/Lib/site-packages/build/_compat/tarfile.py
venv_pypi/Lib/site-packages/build/_compat/tomllib.py
venv_pypi/Lib/site-packages/certifi/__init__.py
venv_pypi/Lib/site-packages/certifi/__main__.py
venv_pypi/Lib/site-packages/certifi/core.py
venv_pypi/Lib/site-packages/certifi/py.typed
venv_pypi/Lib/site-packages/charset_normalizer/__init__.py
venv_pypi/Lib/site-packages/charset_normalizer/__main__.py
venv_pypi/Lib/site-packages/charset_normalizer/api.py
venv_pypi/Lib/site-packages/charset_normalizer/cd.py
venv_pypi/Lib/site-packages/charset_normalizer/constant.py
venv_pypi/Lib/site-packages/charset_normalizer/legacy.py
venv_pypi/Lib/site-packages/charset_normalizer/md.py
venv_pypi/Lib/site-packages/charset_normalizer/models.py
venv_pypi/Lib/site-packages/charset_normalizer/py.typed
venv_pypi/Lib/site-packages/charset_normalizer/utils.py
uois_toolkit-0.1.2.dist-info/METADATA
uois_toolkit-0.1.2.dist-info/WHEEL
uois_toolkit-0.1.2.dist-info/top_level.txt
uois_toolkit-0.1.2.dist-info/RECORD
