Metadata-Version: 2.4
Name: uois_toolkit
Version: 0.1.2
Summary: A toolkit for loading Unseen Object Instance Segmentation (UOIS) datasets.
Author-email: Jishnu Jaykumar Padalunkal <jishnu.p@utdallas.edu>, Avaya Aggarwal <aggarwal.avaya27@gmail.com>, Animesh Maheshwari <animesh.maheshwari02@gmail.com>, IRVL UTD <irvl.utd@gmail.com>
License: MIT
Project-URL: Homepage, https://github.com/OnePunchMonk/uois_toolkit
Project-URL: Issues, https://github.com/OnePunchMonk/uois_toolkit/issues
Classifier: Programming Language :: Python :: 3
Classifier: License :: OSI Approved :: MIT License
Classifier: Operating System :: OS Independent
Requires-Python: >=3.9
License-File: LICENSE
Requires-Dist: torch>=1.9.0
Requires-Dist: torchvision>=0.10.0
Requires-Dist: pytorch-lightning
Requires-Dist: opencv-python>=4.5.0
Requires-Dist: numpy>=1.19.0
Requires-Dist: scipy>=1.5.0
Requires-Dist: pycocotools>=2.0.2
Requires-Dist: open3d>=0.13.0
Requires-Dist: pytest>=7.0
Requires-Dist: imageio
Provides-Extra: detectron2
Requires-Dist: detectron2>=0.6; extra == "detectron2"
Dynamic: license-file
